{"size": 358, "name": "Cluster3", "children": [{"name": "reverse-proxy", "size": 1}, {"name": "dependency-injection", "size": 1}, {"name": "cross-domain", "size": 1}, {"name": "qvt", "size": 1}, {"name": "flash", "size": 1}, {"name": "zxing", "size": 1}, {"name": "nativelibrary", "size": 1}, {"name": "resources", "size": 1}, {"name": "portforwarding", "size": 1}, {"name": "mbeans", "size": 1}, {"name": "facebook", "size": 1}, {"name": "push-notification", "size": 1}, {"name": "weblogic12c", "size": 2}, {"name": "cmd", "size": 1}, {"name": "rabbitmq", "size": 1}, {"name": "visualvm", "size": 1}, {"name": "wicket-6", "size": 1}, {"name": "cookies", "size": 2}, {"name": "netbeans", "size": 7}, {"name": "video", "size": 1}, {"name": "plugins", "size": 1}, {"name": "port", "size": 4}, {"name": "netty", "size": 1}, {"name": "jboss", "size": 4}, {"name": "mathjax", "size": 1}, {"name": ".war", "size": 1}, {"name": "jsf-2", "size": 2}, {"name": "tags", "size": 1}, {"name": "ubuntu", "size": 1}, {"name": "apache", "size": 4}, {"name": "path", "size": 1}, {"name": "design", "size": 1}, {"name": "jax-ws", "size": 2}, {"name": "java-server", "size": 1}, {"name": "travis-ci", "size": 1}, {"name": "action", "size": 1}, {"name": "static-methods", "size": 1}, {"name": "ipc", "size": 1}, {"name": "unix", "size": 1}, {"name": "parameter-passing", "size": 1}, {"name": "logback", "size": 1}, {"name": "jbutton", "size": 1}, {"name": "cloud", "size": 2}, {"name": "regex", "size": 1}, {"name": "javacv", "size": 1}, {"name": "google-app-engine", "size": 3}, {"name": "playframework-2.0", "size": 3}, {"name": "properties", "size": 2}, {"name": "iphone", "size": 1}, {"name": "https", "size": 3}, {"name": "vaadin7", "size": 1}, {"name": "annotations", "size": 2}, {"name": "authorization", "size": 1}, {"name": "shopping-cart", "size": 1}, {"name": "iis", "size": 1}, {"name": "itext", "size": 1}, {"name": "scheduled-tasks", "size": 1}, {"name": "oop", "size": 1}, {"name": "url-parameters", "size": 1}, {"name": "cas", "size": 1}, {"name": "mq", "size": 1}, {"name": "business-objects", "size": 1}, {"name": "guice-servlet", "size": 1}, {"name": "sql-injection", "size": 1}, {"name": "pci-compliance", "size": 1}, {"name": "race-condition", "size": 1}, {"name": "captcha", "size": 1}, {"name": "signed-applet", "size": 1}, {"name": "dwr", "size": 1}, {"name": "struts2", "size": 11}, {"name": "threadpool", "size": 1}, {"name": "globalization", "size": 2}, {"name": "com4j", "size": 1}, {"name": "websphere-8", "size": 1}, {"name": "csv", "size": 1}, {"name": "google-apps-for-education", "size": 1}, {"name": "css", "size": 2}, {"name": "session-cookies", "size": 1}, {"name": "apple-push-notifications", "size": 1}, {"name": "url-rewriting", "size": 5}, {"name": "diagram", "size": 1}, {"name": "date", "size": 1}, {"name": "response", "size": 1}, {"name": "source-code-protection", "size": 1}, {"name": "google-cloud-sql", "size": 1}, {"name": "github", "size": 1}, {"name": "hikaricp", "size": 1}, {"name": "bootstrap", "size": 1}, {"name": "e-commerce", "size": 1}, {"name": "hsqldb", "size": 1}, {"name": "thread-safety", "size": 1}, {"name": "webpage", "size": 1}, {"name": "weblogic11g", "size": 1}, {"name": "jni", "size": 1}, {"name": "forms", "size": 2}, {"name": "client-certificates", "size": 1}, {"name": "glassfish", "size": 6}, {"name": "multithreading", "size": 5}, {"name": "playframework", "size": 3}, {"name": "web.xml", "size": 6}, {"name": "ms-word", "size": 1}, {"name": "business-objects-sdk", "size": 1}, {"name": "extjs4", "size": 1}, {"name": "jsf-1.2", "size": 1}, {"name": ".net", "size": 1}, {"name": "refresh", "size": 1}, {"name": "gradle", "size": 3}, {"name": "jmeter", "size": 1}, {"name": "google-oauth", "size": 1}, {"name": "single-sign-on", "size": 4}, {"name": "static", "size": 1}, {"name": "log-analysis", "size": 1}, {"name": "command-line", "size": 1}, {"name": "factory", "size": 1}, {"name": "ejb", "size": 2}, {"name": "barcode-scanner", "size": 1}, {"name": "filewriter", "size": 1}, {"name": "long-polling", "size": 1}, {"name": "hibernate", "size": 5}, {"name": "sbt", "size": 1}, {"name": "localization", "size": 2}, {"name": "eventlistener", "size": 1}, {"name": "ajax", "size": 1}, {"name": "proxy", "size": 1}, {"name": "logging", "size": 3}, {"name": "netbeans-8", "size": 1}, {"name": "session-variables", "size": 1}, {"name": "swing", "size": 1}, {"name": "encoding", "size": 1}, {"name": "variables", "size": 1}, {"name": "client-side", "size": 1}, {"name": "jetty", "size": 5}, {"name": "java-6", "size": 1}, {"name": "java-8", "size": 1}, {"name": "scoping", "size": 1}, {"name": "smartgwt", "size": 1}, {"name": "struts", "size": 2}, {"name": "system", "size": 1}, {"name": "weblogic", "size": 5}, {"name": "servletcontextlistener", "size": 1}, {"name": "progress-bar", "size": 1}, {"name": "front-controller", "size": 2}, {"name": "jndi", "size": 3}, {"name": "freeze", "size": 1}, {"name": "jquery", "size": 1}, {"name": ".htaccess", "size": 1}, {"name": "tree", "size": 1}, {"name": "liferay", "size": 1}, {"name": "jersey-2.0", "size": 1}, {"name": "applet", "size": 6}, {"name": "file-upload", "size": 1}, {"name": "jodconverter", "size": 1}, {"name": "oc4j", "size": 1}, {"name": "web-api", "size": 1}, {"name": "browser", "size": 1}, {"name": "debugging", "size": 1}, {"name": "protocol-buffers", "size": 1}, {"name": "websocket", "size": 2}, {"name": "rewrite", "size": 1}, {"name": "favicon", "size": 1}, {"name": "jasper-reports", "size": 1}, {"name": "angularjs", "size": 2}, {"name": "google-form", "size": 1}, {"name": "character-encoding", "size": 1}, {"name": "wcs", "size": 1}, {"name": "glassfish-3", "size": 2}, {"name": "jboss7.x", "size": 4}, {"name": "build", "size": 2}, {"name": "performance", "size": 1}, {"name": "soap", "size": 1}, {"name": "jsf", "size": 6}, {"name": "glassfish-4", "size": 2}, {"name": "raspberry-pi", "size": 1}, {"name": "jsp", "size": 32}, {"name": "ssl-certificate", "size": 1}, {"name": "class", "size": 3}, {"name": "oracle11g", "size": 1}, {"name": "latex", "size": 1}, {"name": "executable-jar", "size": 2}, {"name": "windows", "size": 2}, {"name": "classloader", "size": 1}, {"name": "uri", "size": 1}, {"name": "caching", "size": 3}, {"name": "catalina", "size": 1}, {"name": "playframework-2.3", "size": 1}, {"name": "session", "size": 9}, {"name": "shibboleth", "size": 1}, {"name": "redirect", "size": 3}, {"name": "parameters", "size": 1}, {"name": "jar", "size": 4}, {"name": "java-ee-7", "size": 2}, {"name": "java-ee-6", "size": 1}, {"name": "ldap", "size": 1}, {"name": "model-view-controller", "size": 1}, {"name": "stripes", "size": 1}, {"name": "listener", "size": 1}, {"name": "ssl", "size": 1}, {"name": "synchronization", "size": 1}, {"name": "ssh", "size": 1}, {"name": "csrf", "size": 3}, {"name": "business-process", "size": 1}, {"name": "pdf-generation", "size": 2}, {"name": "design-patterns", "size": 3}, {"name": "activiti", "size": 1}, {"name": "wildfly", "size": 1}, {"name": "architecture", "size": 3}, {"name": "facebook-access-token", "size": 1}, {"name": "csrf-protection", "size": 1}, {"name": "bitcoin-testnet", "size": 1}, {"name": "concurrency", "size": 2}, {"name": "workmanagers", "size": 1}, {"name": "javasound", "size": 1}, {"name": "web-services", "size": 11}, {"name": "legacy", "size": 1}, {"name": "user-interface", "size": 1}, {"name": "javabeans", "size": 1}, {"name": "web-applications", "size": 341}, {"name": "php", "size": 1}, {"name": "load-testing", "size": 1}, {"name": "dll", "size": 1}, {"name": "state", "size": 1}, {"name": "google-cloud-storage", "size": 1}, {"name": "popup", "size": 1}, {"name": "hotdeploy", "size": 1}, {"name": "websphere", "size": 8}, {"name": "japplet", "size": 1}, {"name": "javascript", "size": 15}, {"name": "scalability", "size": 1}, {"name": "html5", "size": 5}, {"name": "static-resource", "size": 1}, {"name": "c", "size": 1}, {"name": "gwt", "size": 5}, {"name": "pdf", "size": 4}, {"name": "jersey", "size": 6}, {"name": "applicationcontext", "size": 1}, {"name": "web-config", "size": 1}, {"name": "servlet-3.0", "size": 1}, {"name": "linux", "size": 7}, {"name": "jnlp", "size": 1}, {"name": "java", "size": 358}, {"name": "guice", "size": 1}, {"name": "json", "size": 1}, {"name": "psexec", "size": 1}, {"name": "audio-streaming", "size": 2}, {"name": "bpmn", "size": 1}, {"name": "web-application-project", "size": 1}, {"name": "frameworks", "size": 1}, {"name": "parse.com", "size": 1}, {"name": "jpa", "size": 3}, {"name": "web-application-design", "size": 1}, {"name": "quartz-scheduler", "size": 1}, {"name": "io", "size": 2}, {"name": "ognl", "size": 1}, {"name": "oauth2client", "size": 1}, {"name": "vaadin", "size": 4}, {"name": "httprequest", "size": 2}, {"name": "servlets", "size": 39}, {"name": "classpath", "size": 2}, {"name": "angular-ui-bootstrap", "size": 1}, {"name": "authentication", "size": 3}, {"name": "html", "size": 14}, {"name": "environment-variables", "size": 1}, {"name": "document", "size": 1}, {"name": "log4j", "size": 1}, {"name": "shiro", "size": 1}, {"name": "templates", "size": 1}, {"name": "passwords", "size": 2}, {"name": "http", "size": 7}, {"name": "screenshot", "size": 1}, {"name": "getparameter", "size": 1}, {"name": "user", "size": 1}, {"name": "connection-pooling", "size": 1}, {"name": "task", "size": 1}, {"name": "reflection", "size": 1}, {"name": "database", "size": 7}, {"name": "model", "size": 1}, {"name": "akka", "size": 2}, {"name": "web-deployment", "size": 1}, {"name": "horizontal-scaling", "size": 1}, {"name": "java-web-start", "size": 1}, {"name": "selenium-webdriver", "size": 1}, {"name": "http-status-code-301", "size": 1}, {"name": "rest", "size": 4}, {"name": "mysql", "size": 5}, {"name": "internationalization", "size": 2}, {"name": "garbage-collection", "size": 2}, {"name": "web", "size": 11}, {"name": "java-ee", "size": 30}, {"name": "struct", "size": 1}, {"name": "opencv", "size": 1}, {"name": "application-server", "size": 2}, {"name": "save", "size": 1}, {"name": "database-design", "size": 1}, {"name": "css3", "size": 1}, {"name": "message-queue", "size": 1}, {"name": "dart", "size": 2}, {"name": "jstl", "size": 2}, {"name": "deployment", "size": 4}, {"name": "using", "size": 1}, {"name": "httpsession", "size": 1}, {"name": "grizzly", "size": 1}, {"name": "resin", "size": 1}, {"name": "server", "size": 2}, {"name": "security", "size": 6}, {"name": "mod-rewrite", "size": 1}, {"name": "jersey-1.0", "size": 2}, {"name": "twitter", "size": 1}, {"name": "scala", "size": 3}, {"name": "integration", "size": 1}, {"name": "shared-resource", "size": 1}, {"name": "intellij-idea", "size": 3}, {"name": "localhost", "size": 1}, {"name": "cors", "size": 1}, {"name": "wsdl", "size": 1}, {"name": "servlet-filters", "size": 4}, {"name": "tuckey-urlrewrite-filter", "size": 18}, {"name": "websphere-6.1", "size": 1}, {"name": "oracle-adf", "size": 1}, {"name": "datasource", "size": 2}, {"name": "runtime", "size": 1}, {"name": "block", "size": 1}, {"name": "h2", "size": 1}, {"name": "blockchain", "size": 1}, {"name": "image", "size": 2}, {"name": "embedded-jetty", "size": 1}, {"name": "wicket", "size": 6}, {"name": "log4j2", "size": 3}, {"name": "jdbc", "size": 5}, {"name": "vbscript", "size": 1}, {"name": "owasp", "size": 1}, {"name": "heroku", "size": 2}, {"name": "war", "size": 8}, {"name": "activeweb", "size": 2}, {"name": "activemq", "size": 1}, {"name": "converter", "size": 1}, {"name": "hosting", "size": 1}, {"name": "mobile", "size": 2}, {"name": "tomcat7", "size": 6}, {"name": "tomcat6", "size": 3}, {"name": "file", "size": 1}, {"name": "oauth-2.0", "size": 1}, {"name": "timezone", "size": 2}, {"name": "curl", "size": 1}, {"name": "bitcoinj", "size": 1}, {"name": "tomcat8", "size": 5}, {"name": "oas", "size": 1}, {"name": "load-balancing", "size": 1}, {"name": "unit-testing", "size": 1}, {"name": "webserver", "size": 1}, {"name": "wechat", "size": 1}, {"name": "sql", "size": 2}, {"name": "webdriver", "size": 1}, {"name": "tomcat", "size": 41}, {"name": "slf4j", "size": 1}, {"name": "oracle", "size": 2}, {"name": "validation", "size": 1}]}