{"size": 1495, "name": "Cluster50", "children": [{"name": "jinput", "size": 2}, {"name": "osx", "size": 9}, {"name": "kettle", "size": 1}, {"name": "hashmap", "size": 10}, {"name": "iterator", "size": 1}, {"name": "method-call", "size": 1}, {"name": "duplicates", "size": 1}, {"name": ".obj", "size": 1}, {"name": "global", "size": 1}, {"name": "dynamic", "size": 4}, {"name": "m2e", "size": 1}, {"name": "bytecode", "size": 2}, {"name": "jgit", "size": 37}, {"name": "encapsulation", "size": 3}, {"name": "disk", "size": 1}, {"name": "nested-class", "size": 2}, {"name": "naming-conventions", "size": 2}, {"name": "icons", "size": 2}, {"name": "graph", "size": 1}, {"name": "matlab", "size": 1}, {"name": "jvm", "size": 6}, {"name": "nativelibrary", "size": 1}, {"name": "source-tree", "size": 1}, {"name": "jtextarea", "size": 1}, {"name": "resources", "size": 2}, {"name": "unsatisfiedlinkerror", "size": 2}, {"name": "labels", "size": 1}, {"name": "drools-guvnor", "size": 1}, {"name": "void", "size": 2}, {"name": "git-bisect", "size": 1}, {"name": "nosuchfileexception", "size": 1}, {"name": "dynamic-binding", "size": 1}, {"name": "salesforce", "size": 2}, {"name": "tostring", "size": 6}, {"name": "prepared-statement", "size": 1}, {"name": "anonymous", "size": 3}, {"name": "stackoverflow", "size": 2}, {"name": "switch-statement", "size": 2}, {"name": "level", "size": 1}, {"name": "cmd", "size": 2}, {"name": "list", "size": 7}, {"name": "mapreduce", "size": 2}, {"name": "vector", "size": 2}, {"name": "glfw", "size": 2}, {"name": "pbo", "size": 1}, {"name": "towers-of-hanoi", "size": 1}, {"name": "versioning", "size": 1}, {"name": "glsl", "size": 23}, {"name": "reentrantlock", "size": 1}, {"name": "zero", "size": 2}, {"name": "bitstring", "size": 1}, {"name": "design", "size": 6}, {"name": "java-util-scanner", "size": 2}, {"name": "plugins", "size": 3}, {"name": "click", "size": 1}, {"name": "git-clone", "size": 1}, {"name": "workflow", "size": 1}, {"name": "perlin-noise", "size": 1}, {"name": "vertex-shader", "size": 1}, {"name": "gaming", "size": 1}, {"name": "version", "size": 1}, {"name": "intellij-13", "size": 2}, {"name": "intersect", "size": 1}, {"name": "blender", "size": 1}, {"name": "anti-piracy", "size": 1}, {"name": "public", "size": 5}, {"name": "3d", "size": 21}, {"name": "textures", "size": 24}, {"name": "text-files", "size": 1}, {"name": "barcode", "size": 1}, {"name": "vertex-buffer", "size": 1}, {"name": "compilation", "size": 12}, {"name": "equals", "size": 3}, {"name": "modular", "size": 1}, {"name": "javamail", "size": 1}, {"name": "ubuntu", "size": 1}, {"name": "apache", "size": 3}, {"name": "implicit", "size": 1}, {"name": "windows-7", "size": 1}, {"name": "circular-reference", "size": 1}, {"name": "search", "size": 1}, {"name": "culling", "size": 2}, {"name": "objectinputstream", "size": 1}, {"name": "vbo", "size": 19}, {"name": "shader", "size": 14}, {"name": "getter-setter", "size": 3}, {"name": "heightmap", "size": 3}, {"name": "eclipse-plugin", "size": 2}, {"name": "selectionchanging", "size": 1}, {"name": "static-methods", "size": 1}, {"name": "minecraft", "size": 1}, {"name": "glu", "size": 3}, {"name": "keylistener", "size": 1}, {"name": "render-to-texture", "size": 1}, {"name": "greenfoot", "size": 1}, {"name": "text-rendering", "size": 1}, {"name": "projection", "size": 2}, {"name": "gamepad", "size": 2}, {"name": "ray-picking", "size": 2}, {"name": "private", "size": 10}, {"name": "vim", "size": 1}, {"name": "boolean", "size": 3}, {"name": "names", "size": 1}, {"name": "parameter-passing", "size": 4}, {"name": "fbo", "size": 1}, {"name": "jbutton", "size": 3}, {"name": "intellij-idea", "size": 14}, {"name": "dynamic-class-creation", "size": 1}, {"name": "instantiation", "size": 7}, {"name": "hudson", "size": 1}, {"name": "keycode", "size": 1}, {"name": "invoices", "size": 1}, {"name": "call", "size": 5}, {"name": "memory", "size": 5}, {"name": "scope", "size": 2}, {"name": "annotations", "size": 3}, {"name": "diagrams", "size": 1}, {"name": "fractions", "size": 2}, {"name": "git-add", "size": 1}, {"name": "jms", "size": 1}, {"name": "ubuntu-13.10", "size": 1}, {"name": "actionlistener", "size": 3}, {"name": "stencil-buffer", "size": 1}, {"name": "hashcode", "size": 1}, {"name": "oop", "size": 58}, {"name": "git-branch", "size": 2}, {"name": "jlabel", "size": 1}, {"name": "powermock", "size": 1}, {"name": "folder", "size": 1}, {"name": "resize", "size": 1}, {"name": "include", "size": 2}, {"name": "currency", "size": 1}, {"name": "this", "size": 5}, {"name": "eclipse", "size": 53}, {"name": "jtable", "size": 1}, {"name": "printing", "size": 3}, {"name": "transparency", "size": 1}, {"name": "scjp", "size": 1}, {"name": "modifier", "size": 1}, {"name": "fetch", "size": 2}, {"name": "local-class", "size": 1}, {"name": "compare", "size": 1}, {"name": "process", "size": 1}, {"name": "javadoc", "size": 3}, {"name": "collision", "size": 4}, {"name": "jmenubar", "size": 1}, {"name": "numbers", "size": 4}, {"name": "pong", "size": 4}, {"name": "counting", "size": 1}, {"name": "copy-constructor", "size": 1}, {"name": "expandable", "size": 1}, {"name": "awt-eventqueue", "size": 1}, {"name": "native", "size": 1}, {"name": "inheritance", "size": 42}, {"name": "non-unicode", "size": 1}, {"name": "getresource", "size": 1}, {"name": "fps", "size": 5}, {"name": "tile", "size": 2}, {"name": "xhtml", "size": 1}, {"name": "csv", "size": 2}, {"name": "map", "size": 3}, {"name": "poker", "size": 1}, {"name": "timedelta", "size": 1}, {"name": "binary", "size": 1}, {"name": "clone", "size": 2}, {"name": "diagram", "size": 1}, {"name": "openal", "size": 6}, {"name": "mesh", "size": 1}, {"name": "lighting", "size": 1}, {"name": "arquillian", "size": 1}, {"name": "commit", "size": 1}, {"name": "multiple-inheritance", "size": 4}, {"name": "constants", "size": 2}, {"name": "util", "size": 1}, {"name": "github", "size": 17}, {"name": "auto-generate", "size": 1}, {"name": "fragment-shader", "size": 1}, {"name": "documentation", "size": 2}, {"name": "grails", "size": 1}, {"name": "bufferedimage", "size": 3}, {"name": "stash", "size": 2}, {"name": "hsqldb", "size": 1}, {"name": "nvidia", "size": 1}, {"name": "osgi", "size": 1}, {"name": "order", "size": 2}, {"name": "sharepoint", "size": 1}, {"name": "namespaces", "size": 1}, {"name": "hierarchy", "size": 4}, {"name": "cloudbees", "size": 1}, {"name": "deobfuscation", "size": 1}, {"name": "joptionpane", "size": 3}, {"name": "entity", "size": 1}, {"name": "awtutilities", "size": 1}, {"name": "jmonkeyengine", "size": 2}, {"name": "keyboard", "size": 2}, {"name": "jni", "size": 2}, {"name": "infinite-loop", "size": 1}, {"name": "uuid", "size": 1}, {"name": "apex", "size": 2}, {"name": "double-dispatch", "size": 1}, {"name": "coordinates", "size": 1}, {"name": "window", "size": 3}, {"name": "main", "size": 7}, {"name": "arguments", "size": 3}, {"name": "count", "size": 1}, {"name": "return", "size": 10}, {"name": "dynamic-class-loaders", "size": 1}, {"name": "playframework", "size": 2}, {"name": "python", "size": 4}, {"name": "memory-management", "size": 1}, {"name": "indexing", "size": 1}, {"name": "scaling", "size": 1}, {"name": "refactoring", "size": 1}, {"name": "file-download", "size": 1}, {"name": "emf", "size": 1}, {"name": "code-injection", "size": 1}, {"name": "game-engine", "size": 5}, {"name": "unreal-engine4", "size": 1}, {"name": "instanceof", "size": 3}, {"name": "repaint", "size": 2}, {"name": "subproject", "size": 1}, {"name": "hook", "size": 1}, {"name": "edit", "size": 1}, {"name": "up-casting", "size": 1}, {"name": "fonts", "size": 1}, {"name": "labeling", "size": 1}, {"name": "gradle", "size": 5}, {"name": "2d", "size": 10}, {"name": "merge", "size": 1}, {"name": "token", "size": 1}, {"name": "typeinitializer", "size": 1}, {"name": "timeout", "size": 1}, {"name": "repeating", "size": 1}, {"name": "jmeter", "size": 1}, {"name": "voxel", "size": 4}, {"name": "bluej", "size": 2}, {"name": "memory-leaks", "size": 1}, {"name": "alphablending", "size": 3}, {"name": "maven-plugin", "size": 2}, {"name": "functional-programming", "size": 1}, {"name": "conventions", "size": 1}, {"name": "loops", "size": 3}, {"name": "naming", "size": 1}, {"name": "lzma", "size": 1}, {"name": "canvas", "size": 2}, {"name": "matrix", "size": 8}, {"name": "command-line", "size": 1}, {"name": "multiplayer", "size": 1}, {"name": "dcm4che", "size": 1}, {"name": "mahout", "size": 1}, {"name": "collisions", "size": 1}, {"name": "generics", "size": 29}, {"name": "filewriter", "size": 1}, {"name": "get", "size": 2}, {"name": "twitter4j", "size": 1}, {"name": "math", "size": 5}, {"name": "hibernate", "size": 1}, {"name": "sbt", "size": 1}, {"name": "hashset", "size": 1}, {"name": "amazon-web-services", "size": 1}, {"name": "eventlistener", "size": 1}, {"name": "dependencies", "size": 7}, {"name": "proxy", "size": 1}, {"name": "members", "size": 1}, {"name": "byte", "size": 1}, {"name": "bash", "size": 1}, {"name": "md5", "size": 1}, {"name": "unique", "size": 1}, {"name": "package-structuring", "size": 1}, {"name": "client-server", "size": 2}, {"name": "midi", "size": 2}, {"name": "instance-variables", "size": 1}, {"name": "javafx", "size": 2}, {"name": "timer", "size": 2}, {"name": "swing", "size": 44}, {"name": "mouse-picking", "size": 1}, {"name": "ancestor", "size": 1}, {"name": "maven-3", "size": 1}, {"name": "render", "size": 2}, {"name": "encoding", "size": 1}, {"name": "variables", "size": 37}, {"name": "m2eclipse", "size": 1}, {"name": "nested", "size": 4}, {"name": "instances", "size": 3}, {"name": "jcombobox", "size": 2}, {"name": "rational-numbers", "size": 1}, {"name": "orthographic", "size": 2}, {"name": "abstract-class", "size": 3}, {"name": "java-8", "size": 1}, {"name": "sounds", "size": 1}, {"name": "wavefront", "size": 2}, {"name": "size", "size": 1}, {"name": "php", "size": 3}, {"name": "weka", "size": 1}, {"name": "dump", "size": 1}, {"name": "service", "size": 1}, {"name": "batch-file", "size": 1}, {"name": "struts", "size": 1}, {"name": "wrapper", "size": 3}, {"name": "paint", "size": 3}, {"name": "multitexturing", "size": 1}, {"name": "types", "size": 11}, {"name": "convention", "size": 1}, {"name": "crash-dumps", "size": 1}, {"name": "bits", "size": 1}, {"name": "final", "size": 3}, {"name": "hud", "size": 1}, {"name": "decompiler", "size": 1}, {"name": "shell", "size": 1}, {"name": "terrain", "size": 1}, {"name": "immediate", "size": 1}, {"name": "task", "size": 1}, {"name": "getter", "size": 6}, {"name": "push", "size": 4}, {"name": "while-loop", "size": 1}, {"name": "gson", "size": 1}, {"name": "network-programming", "size": 1}, {"name": "double", "size": 1}, {"name": "arraybuffer", "size": 1}, {"name": "tree", "size": 3}, {"name": "project", "size": 2}, {"name": "applet", "size": 13}, {"name": "protected", "size": 3}, {"name": "amazon-s3", "size": 1}, {"name": "charsequence", "size": 1}, {"name": "2d-games", "size": 1}, {"name": "debugging", "size": 3}, {"name": "addressing", "size": 1}, {"name": "displaylist", "size": 2}, {"name": "variable-scope", "size": 2}, {"name": "fieldofview", "size": 1}, {"name": "generalization", "size": 1}, {"name": "ant", "size": 6}, {"name": "compareto", "size": 2}, {"name": "recover", "size": 1}, {"name": "angle", "size": 1}, {"name": "awtrobot", "size": 2}, {"name": "scenebuilder", "size": 1}, {"name": "self", "size": 1}, {"name": "mipmaps", "size": 1}, {"name": "instance", "size": 25}, {"name": "accessor", "size": 1}, {"name": "animation", "size": 1}, {"name": "type-parameter", "size": 1}, {"name": "build", "size": 2}, {"name": "performance", "size": 11}, {"name": "local-variables", "size": 1}, {"name": "aliasing", "size": 1}, {"name": "openshift", "size": 1}, {"name": "jsf", "size": 2}, {"name": "warnings", "size": 1}, {"name": "buffer", "size": 2}, {"name": "noclassdeffounderror", "size": 3}, {"name": "awt", "size": 6}, {"name": "bsp", "size": 1}, {"name": "extending", "size": 1}, {"name": "non-static", "size": 1}, {"name": "preset", "size": 1}, {"name": "pentaho", "size": 1}, {"name": "test-class", "size": 1}, {"name": "alpha", "size": 2}, {"name": "class", "size": 939}, {"name": "exe", "size": 1}, {"name": "executable-jar", "size": 1}, {"name": "windows", "size": 6}, {"name": "classloader", "size": 19}, {"name": "anonymous-inner-class", "size": 2}, {"name": "blend", "size": 1}, {"name": "text", "size": 5}, {"name": "random", "size": 9}, {"name": "syntax", "size": 2}, {"name": "node.js", "size": 1}, {"name": "colors", "size": 4}, {"name": "bytebuffer", "size": 1}, {"name": "flexjson", "size": 1}, {"name": "game-loop", "size": 1}, {"name": "java.lang.class", "size": 1}, {"name": "find", "size": 2}, {"name": "setter", "size": 4}, {"name": "jsch", "size": 1}, {"name": "depth", "size": 1}, {"name": "layout", "size": 1}, {"name": "vertex-array-object", "size": 2}, {"name": "parameters", "size": 9}, {"name": "menu", "size": 3}, {"name": "explain", "size": 1}, {"name": "public-members", "size": 1}, {"name": "jar", "size": 35}, {"name": "controls", "size": 1}, {"name": "console", "size": 2}, {"name": "terminal", "size": 2}, {"name": "excel-interop", "size": 1}, {"name": "override", "size": 4}, {"name": "jad", "size": 1}, {"name": "reset", "size": 1}, {"name": "move", "size": 1}, {"name": "buildpath", "size": 1}, {"name": "ubuntu-12.04", "size": 1}, {"name": "compiled", "size": 1}, {"name": "pass-by-reference", "size": 1}, {"name": "blinking", "size": 1}, {"name": "listener", "size": 1}, {"name": "ssl", "size": 1}, {"name": "ssh", "size": 5}, {"name": "cherry-pick", "size": 1}, {"name": "distortion", "size": 1}, {"name": "cloud9-ide", "size": 1}, {"name": "jtextfield", "size": 2}, {"name": "design-patterns", "size": 14}, {"name": "egit", "size": 7}, {"name": "idioms", "size": 1}, {"name": "queue", "size": 1}, {"name": "c++", "size": 9}, {"name": "patch", "size": 1}, {"name": "arrays", "size": 2}, {"name": "architecture", "size": 1}, {"name": "movement", "size": 2}, {"name": "art", "size": 1}, {"name": "unicode", "size": 1}, {"name": "reference", "size": 9}, {"name": "drools", "size": 1}, {"name": "frame", "size": 4}, {"name": "startup", "size": 1}, {"name": "closures", "size": 1}, {"name": "freeze", "size": 1}, {"name": "writable", "size": 1}, {"name": "analytics", "size": 1}, {"name": "user-interface", "size": 14}, {"name": "calendar", "size": 1}, {"name": "graphhopper", "size": 1}, {"name": "reverse-engineering", "size": 2}, {"name": "fullscreen", "size": 1}, {"name": "extend", "size": 5}, {"name": "urlclassloader", "size": 1}, {"name": "runtime", "size": 4}, {"name": "scala-java-interop", "size": 1}, {"name": "dll", "size": 2}, {"name": "libraries", "size": 2}, {"name": "macros", "size": 1}, {"name": "liquibase", "size": 1}, {"name": "class-design", "size": 1}, {"name": "import", "size": 11}, {"name": "email", "size": 1}, {"name": "comparable", "size": 1}, {"name": "access-modifiers", "size": 1}, {"name": "parent", "size": 3}, {"name": "javascript", "size": 4}, {"name": "key", "size": 1}, {"name": "matlab-java", "size": 1}, {"name": "interface", "size": 32}, {"name": "serialization", "size": 5}, {"name": "packages", "size": 2}, {"name": "runtime-error", "size": 2}, {"name": "pixels", "size": 1}, {"name": "variable-declaration", "size": 1}, {"name": "c", "size": 1}, {"name": "windows-8", "size": 1}, {"name": "arraylist", "size": 1}, {"name": "gwt", "size": 2}, {"name": "bufferedreader", "size": 1}, {"name": "ioexception", "size": 1}, {"name": "logic", "size": 3}, {"name": "global-variables", "size": 2}, {"name": "zbuffer", "size": 1}, {"name": "load", "size": 4}, {"name": "swingworker", "size": 1}, {"name": "bamboo", "size": 1}, {"name": "point", "size": 2}, {"name": "deserialization", "size": 1}, {"name": "loader", "size": 1}, {"name": "version-control", "size": 6}, {"name": "filechooser", "size": 1}, {"name": "linux", "size": 7}, {"name": "diff", "size": 2}, {"name": "layout-manager", "size": 1}, {"name": "graphics", "size": 14}, {"name": "rtti", "size": 1}, {"name": "java", "size": 1494}, {"name": "symbols", "size": 1}, {"name": "opencv", "size": 1}, {"name": "destructor", "size": 1}, {"name": "twain", "size": 1}, {"name": "image-manipulation", "size": 1}, {"name": "object-oriented-analysis", "size": 2}, {"name": "glreadpixels", "size": 1}, {"name": "jlist", "size": 1}, {"name": "inner-classes", "size": 12}, {"name": "containers", "size": 1}, {"name": "define", "size": 1}, {"name": "sprite", "size": 2}, {"name": "system.out", "size": 1}, {"name": "c#", "size": 2}, {"name": "libgdx", "size": 2}, {"name": "system.in", "size": 1}, {"name": "comboboxmodel", "size": 1}, {"name": "assert", "size": 1}, {"name": "overloading", "size": 1}, {"name": "fest", "size": 1}, {"name": "object-destruction", "size": 1}, {"name": "declaration", "size": 2}, {"name": "self-modifying", "size": 1}, {"name": "acm-java-libraries", "size": 1}, {"name": "api-design", "size": 1}, {"name": "protocols", "size": 1}, {"name": "floating-point", "size": 1}, {"name": "exception", "size": 1}, {"name": "frameworks", "size": 1}, {"name": "optimization", "size": 2}, {"name": "behavior", "size": 1}, {"name": "treeset", "size": 1}, {"name": "rename", "size": 2}, {"name": "project-management", "size": 1}, {"name": "digital-ocean", "size": 1}, {"name": "data-structures", "size": 1}, {"name": "ip", "size": 1}, {"name": "calculator", "size": 2}, {"name": "classnotfound", "size": 1}, {"name": "treemap", "size": 1}, {"name": "windowstate", "size": 1}, {"name": "stringtokenizer", "size": 1}, {"name": "io", "size": 1}, {"name": "mouse", "size": 5}, {"name": "wordnet", "size": 2}, {"name": "capture", "size": 1}, {"name": "voxels", "size": 1}, {"name": "classpath", "size": 7}, {"name": "hadoop", "size": 3}, {"name": "member", "size": 2}, {"name": "split", "size": 1}, {"name": "texture2d", "size": 2}, {"name": "events", "size": 1}, {"name": "interpolation", "size": 1}, {"name": "templates", "size": 1}, {"name": "classnotfoundexception", "size": 5}, {"name": "pixel-perfect", "size": 1}, {"name": "initialization", "size": 6}, {"name": "hang", "size": 1}, {"name": "automation", "size": 1}, {"name": "language-concepts", "size": 1}, {"name": "portal", "size": 1}, {"name": "user", "size": 1}, {"name": "attributes", "size": 1}, {"name": "linked-list", "size": 6}, {"name": "kie", "size": 1}, {"name": "implements", "size": 3}, {"name": "polymorphism", "size": 6}, {"name": "code-reuse", "size": 1}, {"name": "jframe", "size": 10}, {"name": "reflection", "size": 29}, {"name": "database", "size": 1}, {"name": "builder", "size": 1}, {"name": "projection-matrix", "size": 2}, {"name": "flags", "size": 1}, {"name": "components", "size": 2}, {"name": "model", "size": 2}, {"name": "audio", "size": 10}, {"name": "drawing", "size": 1}, {"name": "web-deployment", "size": 1}, {"name": "file-io", "size": 1}, {"name": "jaws-wordnet", "size": 1}, {"name": "opengl-3", "size": 1}, {"name": "human", "size": 1}, {"name": "mysql", "size": 1}, {"name": "shuffle", "size": 1}, {"name": "jdeveloper", "size": 1}, {"name": "rotation", "size": 5}, {"name": "web", "size": 1}, {"name": "loading", "size": 1}, {"name": "java-ee", "size": 1}, {"name": "keyevent", "size": 1}, {"name": "jprofiler", "size": 1}, {"name": "opencl", "size": 1}, {"name": "source", "size": 2}, {"name": "extends", "size": 14}, {"name": "jmenuitem", "size": 1}, {"name": "application-server", "size": 1}, {"name": "input", "size": 11}, {"name": "save", "size": 1}, {"name": "database-design", "size": 1}, {"name": "chess", "size": 1}, {"name": "styles", "size": 1}, {"name": "shadows", "size": 1}, {"name": "jython", "size": 2}, {"name": "casting", "size": 10}, {"name": "finalize", "size": 1}, {"name": "parent-child", "size": 2}, {"name": "aggregation", "size": 1}, {"name": "mousemove", "size": 1}, {"name": "lwjgl", "size": 421}, {"name": "bcel", "size": 1}, {"name": "deployment", "size": 2}, {"name": "integer", "size": 8}, {"name": "shadow", "size": 1}, {"name": "enums", "size": 5}, {"name": "type-conversion", "size": 1}, {"name": "java-3d", "size": 1}, {"name": "codenameone", "size": 1}, {"name": "jformattedtextfield", "size": 1}, {"name": "case-sensitive", "size": 1}, {"name": "anonymous-class", "size": 5}, {"name": "argument-passing", "size": 1}, {"name": "manifest", "size": 2}, {"name": "collect", "size": 1}, {"name": "api", "size": 4}, {"name": "output", "size": 1}, {"name": "security", "size": 2}, {"name": ".net", "size": 1}, {"name": "methods", "size": 113}, {"name": "jls", "size": 1}, {"name": "opengl-2.0", "size": 1}, {"name": "class-diagram", "size": 2}, {"name": "blending", "size": 2}, {"name": "texture-mapping", "size": 2}, {"name": "export", "size": 1}, {"name": "superclass", "size": 7}, {"name": "return-value", "size": 1}, {"name": "table", "size": 1}, {"name": "round-robin", "size": 1}, {"name": "capability", "size": 1}, {"name": "rsync", "size": 1}, {"name": "jtabbedpane", "size": 1}, {"name": "scala", "size": 5}, {"name": "javax.imageio", "size": 1}, {"name": "static-variables", "size": 1}, {"name": "artificial-intelligence", "size": 2}, {"name": "dynamically-generated", "size": 1}, {"name": "slick", "size": 10}, {"name": "subclass", "size": 20}, {"name": "java-libraries", "size": 1}, {"name": "uml", "size": 7}, {"name": "unchecked-cast", "size": 1}, {"name": "core", "size": 1}, {"name": "deepclone", "size": 1}, {"name": "object", "size": 107}, {"name": "repository", "size": 3}, {"name": "vertex-array", "size": 1}, {"name": "processing", "size": 11}, {"name": "method-overloading", "size": 1}, {"name": "executable", "size": 2}, {"name": "tabbing", "size": 1}, {"name": "properties", "size": 4}, {"name": "hiding", "size": 1}, {"name": "package", "size": 19}, {"name": "hawtio", "size": 1}, {"name": "simulation", "size": 1}, {"name": "datagram", "size": 1}, {"name": "constructor", "size": 44}, {"name": "jedis", "size": 1}, {"name": "clojure", "size": 1}, {"name": "backup", "size": 1}, {"name": "nullpointerexception", "size": 5}, {"name": "soa", "size": 1}, {"name": "primitive", "size": 3}, {"name": "graphics2d", "size": 2}, {"name": "javac", "size": 3}, {"name": "bukkit", "size": 1}, {"name": "image", "size": 10}, {"name": "parsing", "size": 4}, {"name": "rendering", "size": 14}, {"name": "square", "size": 1}, {"name": "syntastic", "size": 1}, {"name": "multiple-monitors", "size": 1}, {"name": "atlassian-sourcetree", "size": 2}, {"name": "access-specifier", "size": 1}, {"name": "git", "size": 138}, {"name": "vao", "size": 3}, {"name": "opengl", "size": 231}, {"name": "heroku", "size": 5}, {"name": "stringbuffer", "size": 1}, {"name": "wav", "size": 1}, {"name": "liferay", "size": 2}, {"name": "function", "size": 7}, {"name": "building", "size": 1}, {"name": "paypal", "size": 1}, {"name": "maven-archetype", "size": 1}, {"name": "overlapping", "size": 1}, {"name": "histogram", "size": 1}, {"name": "code-cleanup", "size": 1}, {"name": "subclassing", "size": 1}, {"name": "runnable", "size": 1}, {"name": "com-interop", "size": 1}, {"name": "uv-mapping", "size": 1}, {"name": "xbox360", "size": 1}, {"name": "framebuffer", "size": 3}, {"name": "gldrawarrays", "size": 1}, {"name": "sdk", "size": 1}, {"name": "groovy", "size": 4}, {"name": "pull", "size": 1}, {"name": "prototype", "size": 2}, {"name": "converter", "size": 1}, {"name": "default", "size": 1}, {"name": "decimalformat", "size": 1}, {"name": "r.java-file", "size": 1}, {"name": "url", "size": 2}, {"name": "compiler-errors", "size": 4}, {"name": "authorization", "size": 1}, {"name": "delete", "size": 1}, {"name": "obfuscation", "size": 1}, {"name": "int", "size": 1}, {"name": "abstract", "size": 18}, {"name": "command", "size": 1}, {"name": "tomcat7", "size": 2}, {"name": "objective-c", "size": 1}, {"name": "jpype", "size": 1}, {"name": "closed-source", "size": 1}, {"name": "acm.graphics", "size": 1}, {"name": "javaparser", "size": 1}, {"name": "java-bytecode-asm", "size": 2}, {"name": "excel", "size": 1}, {"name": "jpanel", "size": 6}, {"name": "matrix-multiplication", "size": 1}, {"name": "introspection", "size": 1}, {"name": "field", "size": 10}, {"name": "multi-level", "size": 1}, {"name": "glulookat", "size": 1}, {"name": "branch", "size": 3}, {"name": "digital", "size": 1}, {"name": "jenkins", "size": 5}, {"name": ".class-file", "size": 3}, {"name": "slick2d", "size": 46}, {"name": "draw", "size": 2}, {"name": "javafx-2", "size": 2}, {"name": "raycasting", "size": 1}, {"name": "jinternalframe", "size": 1}, {"name": "symbol", "size": 3}, {"name": "vertex", "size": 2}, {"name": "bounded-wildcard", "size": 1}, {"name": "oracle", "size": 2}, {"name": "z-order", "size": 1}, {"name": "structure", "size": 1}, {"name": "whitespace", "size": 1}, {"name": "svn", "size": 3}, {"name": "multidimensional-array", "size": 1}, {"name": "bitbucket", "size": 11}, {"name": "language-specifications", "size": 1}, {"name": "java-compiler-api", "size": 1}, {"name": "controller", "size": 3}, {"name": "sftp", "size": 1}, {"name": "classcastexception", "size": 1}, {"name": "validator", "size": 1}, {"name": "textmate", "size": 1}, {"name": "time", "size": 3}, {"name": "directory", "size": 1}, {"name": "collision-detection", "size": 4}, {"name": "validation", "size": 2}, {"name": "resolution", "size": 1}]}