{"topicword": {"Topic9": {"java": 0.014, "database": 0.014, "work": 0.025, "send": 0.027, "connection": 0.024, "client": 0.06, "query": 0.014, "run": 0.023, "response": 0.014}, "Topic8": {"set": 0.028, "java": 0.037, "show": 0.019, "url": 0.019, "object": 0.028, "project": 0.019, "elasticsearch": 0.019, "datasource": 0.037, "class": 0.028, "connect": 0.019}, "Topic1": {"java": 0.025, "socket": 0.018, "create": 0.023, "object": 0.027, "number": 0.024, "send": 0.015, "client": 0.13, "program": 0.023, "console": 0.015}, "Topic0": {"java": 0.017, "tomcat": 0.015, "database": 0.016, "create": 0.019, "work": 0.019, "access": 0.016, "application": 0.048, "connection": 0.056, "datasource": 0.037, "method": 0.027}, "Topic3": {"exception": 0.015, "database": 0.026, "request": 0.019, "instance": 0.017, "call": 0.037, "datasource": 0.016, "post": 0.022, "restful": 0.02, "class": 0.015}, "Topic2": {"web": 0.027, "java": 0.024, "project": 0.022, "work": 0.041, "write": 0.031, "source": 0.03, "file": 0.037, "run": 0.022, "data": 0.018}, "Topic5": {"web": 0.024, "run": 0.026, "create": 0.018, "group": 0.016, "application": 0.026, "client": 0.014, "user": 0.029, "time": 0.03, "java": 0.057}, "Topic4": {"work": 0.018, "eclipse": 0.017, "start": 0.017, "glassfish": 0.045, "datasource": 0.017, "file": 0.03, "put": 0.017, "table": 0.034, "problem": 0.017, "class": 0.023}, "Topic7": {"run": 0.028, "tomcat": 0.028, "show": 0.028, "class": 0.019, "jboss": 0.019, "error": 0.028, "query": 0.019, "configuration": 0.028, "method": 0.046}, "Topic6": {"run": 0.027, "tomcat": 0.02, "database": 0.025, "number": 0.019, "connect": 0.025, "error": 0.029, "report": 0.024, "problem": 0.019, "port": 0.021}}, "wordtopic": {"set": {"Topic8": 0.028}, "show": {"Topic8": 0.019, "Topic7": 0.028}, "eclipse": {"Topic4": 0.017}, "number": {"Topic1": 0.024, "Topic6": 0.019}, "group": {"Topic5": 0.016}, "glassfish": {"Topic4": 0.045}, "connect": {"Topic8": 0.019, "Topic6": 0.025}, "file": {"Topic2": 0.037, "Topic4": 0.03}, "query": {"Topic9": 0.014, "Topic7": 0.019}, "table": {"Topic4": 0.034}, "port": {"Topic6": 0.021}, "jboss": {"Topic7": 0.019}, "access": {"Topic0": 0.016}, "error": {"Topic7": 0.028, "Topic6": 0.029}, "java": {"Topic9": 0.014, "Topic8": 0.037, "Topic1": 0.025, "Topic0": 0.017, "Topic2": 0.024, "Topic5": 0.057}, "start": {"Topic4": 0.017}, "source": {"Topic2": 0.03}, "create": {"Topic1": 0.023, "Topic0": 0.019, "Topic5": 0.018}, "send": {"Topic1": 0.015, "Topic9": 0.027}, "response": {"Topic9": 0.014}, "write": {"Topic2": 0.031}, "application": {"Topic0": 0.048, "Topic5": 0.026}, "program": {"Topic1": 0.023}, "call": {"Topic3": 0.037}, "method": {"Topic0": 0.027, "Topic7": 0.046}, "run": {"Topic9": 0.023, "Topic2": 0.022, "Topic5": 0.026, "Topic7": 0.028, "Topic6": 0.027}, "web": {"Topic2": 0.027, "Topic5": 0.024}, "object": {"Topic1": 0.027, "Topic8": 0.028}, "instance": {"Topic3": 0.017}, "user": {"Topic5": 0.029}, "put": {"Topic4": 0.017}, "console": {"Topic1": 0.015}, "post": {"Topic3": 0.022}, "configuration": {"Topic7": 0.028}, "data": {"Topic2": 0.018}, "class": {"Topic8": 0.028, "Topic3": 0.015, "Topic4": 0.023, "Topic7": 0.019}, "exception": {"Topic3": 0.015}, "socket": {"Topic1": 0.018}, "tomcat": {"Topic0": 0.015, "Topic7": 0.028, "Topic6": 0.02}, "database": {"Topic9": 0.014, "Topic0": 0.016, "Topic3": 0.026, "Topic6": 0.025}, "url": {"Topic8": 0.019}, "work": {"Topic9": 0.025, "Topic0": 0.019, "Topic2": 0.041, "Topic4": 0.018}, "request": {"Topic3": 0.019}, "project": {"Topic8": 0.019, "Topic2": 0.022}, "connection": {"Topic9": 0.024, "Topic0": 0.056}, "client": {"Topic1": 0.13, "Topic9": 0.06, "Topic5": 0.014}, "elasticsearch": {"Topic8": 0.019}, "datasource": {"Topic0": 0.037, "Topic3": 0.016, "Topic4": 0.017, "Topic8": 0.037}, "time": {"Topic5": 0.03}, "report": {"Topic6": 0.024}, "problem": {"Topic4": 0.017, "Topic6": 0.019}, "restful": {"Topic3": 0.02}}, "desc": "server"}