{"topicword": {"Topic9": {"run": 0.018, "app": 0.012, "work": 0.017, "eclipse": 0.028, "application": 0.011, "file": 0.024, "error": 0.034, "line": 0.012, "native": 0.012}, "Topic8": {"java": 0.016, "show": 0.016, "eclipse": 0.015, "proguard": 0.016, "item": 0.018, "add": 0.017, "error": 0.017, "layout": 0.015, "click": 0.016}, "Topic1": {"draw": 0.014, "name": 0.013, "repository": 0.031, "show": 0.015, "button": 0.036, "work": 0.028, "eclipse": 0.014, "field": 0.016, "file": 0.015}, "Topic0": {"play": 0.031, "google": 0.037, "service": 0.034, "create": 0.024, "eclipse": 0.014, "library": 0.021, "project": 0.049, "file": 0.021, "app": 0.014}, "Topic3": {"java": 0.012, "app": 0.016, "work": 0.021, "eclipse": 0.017, "project": 0.027, "file": 0.038, "error": 0.033, "folder": 0.011, "create": 0.015}, "Topic2": {"run": 0.015, "app": 0.034, "eclipse": 0.021, "class": 0.011, "project": 0.019, "file": 0.012, "error": 0.077, "problem": 0.014, "method": 0.014}, "Topic5": {"run": 0.026, "app": 0.023, "work": 0.014, "eclipse": 0.03, "project": 0.047, "add": 0.022, "file": 0.025, "error": 0.008, "problem": 0.024}, "Topic4": {"log": 0.013, "fragment": 0.015, "app": 0.016, "work": 0.023, "class": 0.024, "application": 0.021, "error": 0.021, "activity": 0.015, "method": 0.016}, "Topic7": {"app": 0.012, "image": 0.046, "list": 0.016, "display": 0.013, "add": 0.019, "activity": 0.013, "array": 0.014, "null": 0.019, "button": 0.02}, "Topic6": {"run": 0.015, "fix": 0.009, "work": 0.019, "eclipse": 0.029, "application": 0.016, "emulator": 0.01, "error": 0.02, "test": 0.012, "problem": 0.029}, "Topic19": {"run": 0.017, "app": 0.022, "work": 0.027, "eclipse": 0.022, "library": 0.015, "project": 0.037, "application": 0.015, "error": 0.015, "class": 0.015}, "Topic18": {"run": 0.018, "app": 0.02, "eclipse": 0.018, "display": 0.01, "application": 0.014, "message": 0.011, "error": 0.022, "problem": 0.012, "adapter": 0.014}, "Topic15": {"repository": 0.146, "javac": 0.026, "symbol": 0.011, "library": 0.024, "project": 0.018, "location": 0.013, "error": 0.022, "problem": 0.011, "class": 0.015}, "Topic14": {"show": 0.011, "skip": 0.012, "create": 0.014, "work": 0.022, "eclipse": 0.029, "application": 0.018, "error": 0.02, "problem": 0.018, "frame": 0.013}, "Topic17": {"app": 0.013, "create": 0.033, "eclipse": 0.032, "class": 0.013, "project": 0.037, "file": 0.069, "error": 0.014, "problem": 0.014, "folder": 0.018}, "Topic16": {"app": 0.024, "work": 0.029, "class": 0.017, "application": 0.022, "intent": 0.021, "frame": 0.016, "activity": 0.023, "line": 0.018, "main": 0.026, "button": 0.018}, "Topic11": {"work": 0.013, "eclipse": 0.032, "library": 0.034, "project": 0.066, "add": 0.014, "file": 0.014, "error": 0.025, "import": 0.032, "problem": 0.012}, "Topic10": {"app": 0.032, "work": 0.019, "eclipse": 0.022, "click": 0.015, "project": 0.018, "error": 0.02, "problem": 0.012, "create": 0.012, "button": 0.025}, "Topic13": {"work": 0.012, "screen": 0.035, "object": 0.015, "class": 0.021, "application": 0.014, "splash": 0.012, "call": 0.015, "error": 0.011, "app": 0.012, "method": 0.051}, "Topic12": {"java": 0.044, "jdk": 0.014, "text": 0.014, "app": 0.013, "work": 0.012, "eclipse": 0.011, "error": 0.025, "amp": 0.013, "class": 0.011}, "Topic20": {"run": 0.023, "image": 0.048, "work": 0.013, "eclipse": 0.025, "page": 0.011, "project": 0.014, "button": 0.013, "import": 0.014, "problem": 0.018, "app": 0.014}, "Topic21": {"run": 0.021, "screen": 0.011, "eclipse": 0.033, "project": 0.013, "manager": 0.022, "error": 0.017, "download": 0.014, "java": 0.013, "sdk": 0.022}, "Topic22": {"map": 0.012, "google": 0.017, "run": 0.021, "app": 0.032, "work": 0.02, "eclipse": 0.029, "update": 0.013, "error": 0.014, "sdk": 0.029}, "Topic23": {"run": 0.012, "create": 0.016, "work": 0.028, "eclipse": 0.022, "project": 0.011, "time": 0.012, "problem": 0.012, "app": 0.012, "change": 0.015}}, "wordtopic": {"google": {"Topic0": 0.037, "Topic22": 0.017}, "javac": {"Topic15": 0.026}, "show": {"Topic1": 0.015, "Topic8": 0.016, "Topic14": 0.011}, "list": {"Topic7": 0.016}, "app": {"Topic9": 0.012, "Topic0": 0.014, "Topic3": 0.016, "Topic2": 0.034, "Topic5": 0.023, "Topic4": 0.016, "Topic7": 0.012, "Topic20": 0.014, "Topic22": 0.032, "Topic23": 0.012, "Topic19": 0.022, "Topic18": 0.02, "Topic17": 0.013, "Topic16": 0.024, "Topic10": 0.032, "Topic13": 0.012, "Topic12": 0.013}, "draw": {"Topic1": 0.014}, "library": {"Topic15": 0.024, "Topic0": 0.021, "Topic19": 0.015, "Topic11": 0.034}, "proguard": {"Topic8": 0.016}, "manager": {"Topic21": 0.022}, "file": {"Topic9": 0.024, "Topic1": 0.015, "Topic0": 0.021, "Topic3": 0.038, "Topic2": 0.012, "Topic5": 0.025, "Topic17": 0.069, "Topic11": 0.014}, "amp": {"Topic12": 0.013}, "download": {"Topic21": 0.014}, "adapter": {"Topic18": 0.014}, "array": {"Topic7": 0.014}, "null": {"Topic7": 0.019}, "click": {"Topic8": 0.016, "Topic10": 0.015}, "native": {"Topic9": 0.012}, "java": {"Topic8": 0.016, "Topic3": 0.012, "Topic21": 0.013, "Topic12": 0.044}, "log": {"Topic4": 0.013}, "service": {"Topic0": 0.034}, "application": {"Topic9": 0.011, "Topic4": 0.021, "Topic6": 0.016, "Topic19": 0.015, "Topic18": 0.014, "Topic14": 0.018, "Topic16": 0.022, "Topic13": 0.014}, "create": {"Topic0": 0.024, "Topic3": 0.015, "Topic23": 0.016, "Topic14": 0.014, "Topic17": 0.033, "Topic10": 0.012}, "message": {"Topic18": 0.011}, "symbol": {"Topic15": 0.011}, "field": {"Topic1": 0.016}, "add": {"Topic8": 0.017, "Topic11": 0.014, "Topic5": 0.022, "Topic7": 0.019}, "splash": {"Topic13": 0.012}, "call": {"Topic13": 0.015}, "location": {"Topic15": 0.013}, "text": {"Topic12": 0.014}, "test": {"Topic6": 0.012}, "import": {"Topic20": 0.014, "Topic11": 0.032}, "folder": {"Topic3": 0.011, "Topic17": 0.018}, "main": {"Topic16": 0.026}, "method": {"Topic2": 0.014, "Topic4": 0.016, "Topic13": 0.051}, "page": {"Topic20": 0.011}, "map": {"Topic22": 0.012}, "play": {"Topic0": 0.031}, "object": {"Topic13": 0.015}, "run": {"Topic9": 0.018, "Topic2": 0.015, "Topic5": 0.026, "Topic6": 0.015, "Topic20": 0.023, "Topic21": 0.021, "Topic22": 0.021, "Topic23": 0.012, "Topic19": 0.017, "Topic18": 0.018}, "time": {"Topic23": 0.012}, "repository": {"Topic1": 0.031, "Topic15": 0.146}, "frame": {"Topic14": 0.013, "Topic16": 0.016}, "fragment": {"Topic4": 0.015}, "screen": {"Topic21": 0.011, "Topic13": 0.035}, "activity": {"Topic16": 0.023, "Topic4": 0.015, "Topic7": 0.013}, "update": {"Topic22": 0.013}, "skip": {"Topic14": 0.012}, "layout": {"Topic8": 0.015}, "line": {"Topic9": 0.012, "Topic16": 0.018}, "class": {"Topic2": 0.011, "Topic4": 0.024, "Topic19": 0.015, "Topic15": 0.015, "Topic17": 0.013, "Topic16": 0.017, "Topic13": 0.021, "Topic12": 0.011}, "change": {"Topic23": 0.015}, "sdk": {"Topic21": 0.022, "Topic22": 0.029}, "name": {"Topic1": 0.013}, "jdk": {"Topic12": 0.014}, "button": {"Topic1": 0.036, "Topic20": 0.013, "Topic16": 0.018, "Topic10": 0.025, "Topic7": 0.02}, "work": {"Topic9": 0.017, "Topic1": 0.028, "Topic3": 0.021, "Topic5": 0.014, "Topic4": 0.023, "Topic6": 0.019, "Topic20": 0.013, "Topic22": 0.02, "Topic23": 0.028, "Topic19": 0.027, "Topic14": 0.022, "Topic16": 0.029, "Topic11": 0.013, "Topic10": 0.019, "Topic13": 0.012, "Topic12": 0.012}, "eclipse": {"Topic9": 0.028, "Topic8": 0.015, "Topic1": 0.014, "Topic0": 0.014, "Topic3": 0.017, "Topic2": 0.021, "Topic5": 0.03, "Topic6": 0.029, "Topic20": 0.025, "Topic21": 0.033, "Topic22": 0.029, "Topic23": 0.022, "Topic19": 0.022, "Topic18": 0.018, "Topic14": 0.029, "Topic17": 0.032, "Topic11": 0.032, "Topic10": 0.022, "Topic12": 0.011}, "display": {"Topic18": 0.01, "Topic7": 0.013}, "project": {"Topic0": 0.049, "Topic3": 0.027, "Topic2": 0.019, "Topic5": 0.047, "Topic20": 0.014, "Topic21": 0.013, "Topic23": 0.011, "Topic19": 0.037, "Topic15": 0.018, "Topic17": 0.037, "Topic11": 0.066, "Topic10": 0.018}, "item": {"Topic8": 0.018}, "emulator": {"Topic6": 0.01}, "image": {"Topic20": 0.048, "Topic7": 0.046}, "error": {"Topic9": 0.034, "Topic8": 0.017, "Topic3": 0.033, "Topic2": 0.077, "Topic5": 0.008, "Topic4": 0.021, "Topic6": 0.02, "Topic21": 0.017, "Topic22": 0.014, "Topic19": 0.015, "Topic18": 0.022, "Topic15": 0.022, "Topic14": 0.02, "Topic17": 0.014, "Topic11": 0.025, "Topic10": 0.02, "Topic13": 0.011, "Topic12": 0.025}, "intent": {"Topic16": 0.021}, "problem": {"Topic2": 0.014, "Topic5": 0.024, "Topic6": 0.029, "Topic20": 0.018, "Topic23": 0.012, "Topic18": 0.012, "Topic15": 0.011, "Topic14": 0.018, "Topic17": 0.014, "Topic11": 0.012, "Topic10": 0.012}, "fix": {"Topic6": 0.009}}, "desc": "android"}